<?xml version="1.0" encoding="utf-8" ?><dwsync><file name="collection_hover.png" server="ftp.creativedesignbox.com" local="3612474461" remote="321578193772919752" Dst="-1" /><file name="csv_hover.png" server="ftp.creativedesignbox.com" local="3612474461" remote="321578193772919752" Dst="-1" /><file name="pdf_hover.png" server="ftp.creativedesignbox.com" local="3612474461" remote="321578193772919752" Dst="-1" /><file name="copy_hover.png" server="ftp.creativedesignbox.com" local="3612474461" remote="321578193772919752" Dst="-1" /><file name="background.png" server="ftp.creativedesignbox.com" local="3612474461" remote="321578193772919752" Dst="-1" /><file name="print.png" server="ftp.creativedesignbox.com" local="3612474461" remote="321578193772919752" Dst="-1" /><file name="xls.png" server="ftp.creativedesignbox.com" local="3612474461" remote="321578193772919752" Dst="-1" /><file name="pdf.png" server="ftp.creativedesignbox.com" local="3612474461" remote="321578193772919752" Dst="-1" /><file name="collection.png" server="ftp.creativedesignbox.com" local="3612474461" remote="321578193772919752" Dst="-1" /><file name="xls_hover.png" server="ftp.creativedesignbox.com" local="3612474461" remote="321578193772919752" Dst="-1" /><file name="print_hover.png" server="ftp.creativedesignbox.com" local="3612474461" remote="321578193772919752" Dst="-1" /><file name="csv.png" server="ftp.creativedesignbox.com" local="3612474461" remote="321578193772919752" Dst="-1" /><file name="copy.png" server="ftp.creativedesignbox.com" local="3612474461" remote="321578193772919752" Dst="-1" /></dwsync>